firedis/__init__.py
firedis/common.py
firedis/core.py
firedis/namespace.py
firedis/singlekey.py
firedis-0.1.4.dist-info/METADATA
firedis-0.1.4.dist-info/WHEEL
firedis-0.1.4.dist-info/RECORD
