Metadata-Version: 2.1
Name: firedis
Version: 0.1.4
Summary: Fast, type-safe, custom Namespaces for local Redis
Author-email: Ryan Young <dev@ryayoung.com>
License-Expression: MIT
Classifier: Development Status :: 3 - Alpha
Classifier: Intended Audience :: Developers
Classifier: License :: OSI Approved :: MIT License
Classifier: Operating System :: OS Independent
Classifier: Programming Language :: Python :: 3.11
Classifier: Topic :: Software Development :: Libraries
Requires-Dist: hiredis==3.0.0
Requires-Dist: redis==5.0.8
